jira_ticket_updater/__init__.py
jira_ticket_updater/cli_handlers.py
jira_ticket_updater/jira_api.py
jira_ticket_updater/jira_operations.py
jira_ticket_updater/jira_utils.py
jira_ticket_updater/main.py
jira_ticket_updater-1.0.3.dist-info/licenses/LICENSE
jira_ticket_updater-1.0.3.dist-info/METADATA
jira_ticket_updater-1.0.3.dist-info/WHEEL
jira_ticket_updater-1.0.3.dist-info/entry_points.txt
jira_ticket_updater-1.0.3.dist-info/top_level.txt
jira_ticket_updater-1.0.3.dist-info/RECORD
