Metadata-Version: 2.4
Name: jira-ticket-updater
Version: 1.0.3
Summary: A command-line tool for updating Jira ticket status
Home-page: https://github.com/Pandiyarajk/jira-ticket-updater
Author: Pandiyaraj Karuppasamy
Author-email: Pandiyaraj Karuppasamy <pandiyarajk@live.com>
Maintainer-email: Pandiyaraj Karuppasamy <pandiyarajk@live.com>
License-Expression: MIT
Project-URL: Homepage, https://github.com/Pandiyarajk/jira-ticket-updater
Project-URL: Repository, https://github.com/Pandiyarajk/jira-ticket-updater
Project-URL: Documentation, https://github.com/Pandiyarajk/jira-ticket-updater#readme
Project-URL: Issues, https://github.com/Pandiyarajk/jira-ticket-updater/issues
Project-URL: Changelog, https://github.com/Pandiyarajk/jira-ticket-updater/blob/main/CHANGE_LOG.md
Project-URL: License, https://github.com/Pandiyarajk/jira-ticket-updater/blob/main/LICENSE
Keywords: jira,status-update,automation,devops,workflow
Classifier: Development Status :: 5 - Production/Stable
Classifier: Intended Audience :: Developers
Classifier: Operating System :: Microsoft :: Windows
Classifier: Programming Language :: Python :: 3
Classifier: Programming Language :: Python :: 3.7
Classifier: Programming Language :: Python :: 3.8
Classifier: Programming Language :: Python :: 3.9
Classifier: Programming Language :: Python :: 3.10
Classifier: Programming Language :: Python :: 3.11
Classifier: Programming Language :: Python :: 3.12
Classifier: Programming Language :: Python :: 3.13
Classifier: Topic :: Software Development
Classifier: Topic :: Utilities
Requires-Python: >=3.7
License-File: LICENSE
Requires-Dist: requests>=2.25.0
Dynamic: author
Dynamic: home-page
Dynamic: license-file
Dynamic: requires-python
